__init__.py
crdclib/__init__.py
crdclib/crdclib.py
crdclib/dhqueries.py
crdclib-0.0.14.dist-info/licenses/LICENSE
crdclib-0.0.14.dist-info/METADATA
crdclib-0.0.14.dist-info/WHEEL
crdclib-0.0.14.dist-info/top_level.txt
crdclib-0.0.14.dist-info/RECORD
