Metadata-Version: 2.4
Name: crdclib
Version: 0.0.14
Summary: A collection of functions useful for interactive with parts of the CRDC ecosystem
Author-email: Todd Pihl <todd.pihl@gmail.com>
Project-URL: Homepage, https://github.com/pihltd/CRDCLib
Project-URL: Issues, https://github.com/pihltd/CRDCLib/issues
Classifier: Programming Language :: Python :: 3
Classifier: Programming Language :: Python :: 3.9
Classifier: Programming Language :: Python :: 3.10
Classifier: Programming Language :: Python :: 3.11
Classifier: Programming Language :: Python :: 3.12
Classifier: License :: OSI Approved :: Apache Software License
Classifier: Operating System :: OS Independent
Requires-Python: >=3.9
License-File: LICENSE
Requires-Dist: requests
Requires-Dist: pyyaml
Requires-Dist: bento_meta
Requires-Dist: pandas
Dynamic: license-file
